README.md
setup.py
datetimex/__init__.py
datetimex/error.py
datetimex/formatChinese.py
datetimex/formatTime.py
datetimex/getTime.py
datetimex/legalizationTime.py
datetimex/main.py
datetimex.egg-info/PKG-INFO
datetimex.egg-info/SOURCES.txt
datetimex.egg-info/dependency_links.txt
datetimex.egg-info/top_level.txt
datetimex.egg-info/zip-safe